README.rst
flake8_immediate.py
setup.py
flake8_immediate.egg-info/PKG-INFO
flake8_immediate.egg-info/SOURCES.txt
flake8_immediate.egg-info/dependency_links.txt
flake8_immediate.egg-info/entry_points.txt
flake8_immediate.egg-info/not-zip-safe
flake8_immediate.egg-info/top_level.txt