Metadata-Version: 1.1
Name: flake8-immediate
Version: 0.2
Summary: Enables immediate output for flake8.
Home-page: https://github.com/schlamar/flake8-todo
Author: Marc Schlaich
Author-email: marc.schlaich@gmail.com
License: MIT
Keywords: flake8 immediate output
Platform: UNKNOWN
Classifier: Development Status :: 3 - Alpha
Classifier: Environment :: Console
Classifier: Intended Audience :: Developers
Classifier: License :: OSI Approved :: MIT License
Classifier: Operating System :: OS Independent
Classifier: Programming Language :: Python
Classifier: Programming Language :: Python :: 2
Classifier: Programming Language :: Python :: 3
Classifier: Topic :: Software Development :: Libraries :: Python Modules
Classifier: Topic :: Software Development :: Quality Assurance
